jupyter_cadquery_widgets/__init__.py
jupyter_cadquery_widgets/_version.py
jupyter_cadquery_widgets/labextension/package.json
jupyter_cadquery_widgets/labextension/static/267.529b695ff33536494a7e.js
jupyter_cadquery_widgets/labextension/static/267.529b695ff33536494a7e.js.LICENSE.txt
jupyter_cadquery_widgets/labextension/static/486.93a3797b6736b3346572.js
jupyter_cadquery_widgets/labextension/static/486.93a3797b6736b3346572.js.LICENSE.txt
jupyter_cadquery_widgets/labextension/static/534.ebab46b2dc0757b8c21e.js
jupyter_cadquery_widgets/labextension/static/565.9de4242a84b58e624131.js
jupyter_cadquery_widgets/labextension/static/565.9de4242a84b58e624131.js.LICENSE.txt
jupyter_cadquery_widgets/labextension/static/653.526ab22cb2def80a2c59.js
jupyter_cadquery_widgets/labextension/static/776.57bd506a5a84afbc4fab.js
jupyter_cadquery_widgets/labextension/static/remoteEntry.b835eb8fb10bb4212c35.js
jupyter_cadquery_widgets/labextension/static/style.js
jupyter_cadquery_widgets/nbextension/extension.js
jupyter_cadquery_widgets/nbextension/index.js
jupyter_cadquery_widgets/nbextension/index.js.map
jupyter_cadquery_widgets/widgets/__init__.py
jupyter_cadquery_widgets/widgets/image_button.py
jupyter_cadquery_widgets/widgets/tree_view.py
jupyter_cadquery_widgets-2.0.2.data/data/etc/jupyter/nbconfig/notebook.d/jupyter_cadquery.json
jupyter_cadquery_widgets-2.0.2.data/data/share/jupyter/labextensions/jupyter_cadquery/install.json
jupyter_cadquery_widgets-2.0.2.data/data/share/jupyter/labextensions/jupyter_cadquery/package.json
jupyter_cadquery_widgets-2.0.2.data/data/share/jupyter/labextensions/jupyter_cadquery/static/267.529b695ff33536494a7e.js
jupyter_cadquery_widgets-2.0.2.data/data/share/jupyter/labextensions/jupyter_cadquery/static/267.529b695ff33536494a7e.js.LICENSE.txt
jupyter_cadquery_widgets-2.0.2.data/data/share/jupyter/labextensions/jupyter_cadquery/static/486.93a3797b6736b3346572.js
jupyter_cadquery_widgets-2.0.2.dist-info/LICENSE
jupyter_cadquery_widgets-2.0.2.dist-info/METADATA
jupyter_cadquery_widgets-2.0.2.dist-info/WHEEL
jupyter_cadquery_widgets-2.0.2.dist-info/top_level.txt
jupyter_cadquery_widgets-2.0.2.dist-info/RECORD
