Metadata-Version: 2.1
Name: jupyter-cadquery-widgets
Version: 2.0.2
Summary: A JupyterLab extension.
Home-page: https://github.com/bernhard-42/jupyter-cadquery-widgets
Author: Bernhard Walter
Author-email: b_walter@arcor.de
License: BSD-3-Clause
Keywords: Jupyter,JupyterLab,JupyterLab3
Platform: Linux
Platform: Mac OS X
Platform: Windows
Classifier: License :: OSI Approved :: BSD License
Classifier: Programming Language :: Python
Classifier: Programming Language :: Python :: 3
Classifier: Programming Language :: Python :: 3.6
Classifier: Programming Language :: Python :: 3.7
Classifier: Programming Language :: Python :: 3.8
Classifier: Programming Language :: Python :: 3.9
Classifier: Framework :: Jupyter
Requires-Python: >=3.6
Requires-Dist: jupyterlab (~=3.0)
Requires-Dist: ipywidgets (~=7.6)
Provides-Extra: dev
Requires-Dist: pylint ; extra == 'dev'
Requires-Dist: bumpversion ; extra == 'dev'
Requires-Dist: cookiecutter ; extra == 'dev'
Requires-Dist: twine ; extra == 'dev'
Requires-Dist: jupyter-packaging ; extra == 'dev'
Requires-Dist: black ; extra == 'dev'
Requires-Dist: pyYaml ; extra == 'dev'
